picompress/__init__.py
picompress/compressor.py
picompress/dll/cim.dll
picompress/so/libcim.so
picompress/so/libcim.so.2.0
picompress-4.0.1.dist-info/METADATA
picompress-4.0.1.dist-info/WHEEL
picompress-4.0.1.dist-info/top_level.txt
picompress-4.0.1.dist-info/RECORD
